color/__init__.py
color/_nbdev.py
color/core.py
pcolor/__init__.py
pcolor/_nbdev.py
pcolor/core.py
pcolor-0.0.4.dist-info/LICENSE
pcolor-0.0.4.dist-info/METADATA
pcolor-0.0.4.dist-info/WHEEL
pcolor-0.0.4.dist-info/entry_points.txt
pcolor-0.0.4.dist-info/top_level.txt
pcolor-0.0.4.dist-info/RECORD
