Metadata-Version: 2.1
Name: pcolor
Version: 0.0.4
Summary: specific color scheme
Home-page: https://github.com/catethos/pcolor
Author: catethos
Author-email: cloverethos@gmail.com
License: Apache Software License 2.0
Keywords: some keywords
Platform: UNKNOWN
Classifier: Development Status :: 3 - Alpha
Classifier: Intended Audience :: Developers
Classifier: License :: OSI Approved :: Apache Software License
Classifier: Natural Language :: English
Classifier: Programming Language :: Python :: 3.7
Classifier: Programming Language :: Python :: 3.8
Requires-Python: >=3.7
Requires-Dist: numpy
Requires-Dist: matplotlib
Requires-Dist: seaborn
Requires-Dist: altair
Requires-Dist: pampy
Requires-Dist: pandas
Requires-Dist: vega-datasets
